LICENSE
MANIFEST.in
README.md
setup.py
pygments_ket/__init__.py
pygments_ket.egg-info/PKG-INFO
pygments_ket.egg-info/SOURCES.txt
pygments_ket.egg-info/dependency_links.txt
pygments_ket.egg-info/entry_points.txt
pygments_ket.egg-info/requires.txt
pygments_ket.egg-info/top_level.txt