Metadata-Version: 2.1
Name: pygments-ket
Version: 0.2
Summary: Pygments lexer for Ket.
Home-page: https://gitlab.com/quantum-ket/pygments-ket
Author: Evandro Chagas Ribeiro da Rosa
Author-email: evandro.crr@posgrad.ufsc.br
License: Apache-2.0
Keywords: pygments ket lexer
Platform: UNKNOWN
